iguanaresult2csv/__init__.py
iguanaresult2csv/processing.py
iguanaresult2csv/exec/__init__.py
iguanaresult2csv/exec/run.py
iguanaresult2csv/sparql/get_tasks.sparql
iguanaresult2csv/sparql/task_data.sparql
iguanaresult2csv/sparql/task_data_each_query.sparql
iguanaresult2csv/sparql/task_meta_data.sparql
iguanaresult2csv-3.2.0.dist-info/LICENSE
iguanaresult2csv-3.2.0.dist-info/METADATA
iguanaresult2csv-3.2.0.dist-info/WHEEL
iguanaresult2csv-3.2.0.dist-info/entry_points.txt
iguanaresult2csv-3.2.0.dist-info/top_level.txt
iguanaresult2csv-3.2.0.dist-info/RECORD
