Metadata-Version: 2.1
Name: iguanaresult2csv
Version: 3.2.0
Summary: Convert IGUANA <https://github.com/dice-group/IGUANA> RDF result files to CSV.
Home-page: https://github.com/dice-group/IguanaResult2CSV
Author: Alexander Bigerl
Author-email: info@dice-research.org
License: AGPL v3
Platform: UNKNOWN
Requires-Dist: rdflib (>=5.0.0)
Requires-Dist: requests (>=2.25.1)
Requires-Dist: click (>=7.1.2)
